pandas_ga/__init__.py
pandas_ga-0.1.dist-info/LICENSE
pandas_ga-0.1.dist-info/METADATA
pandas_ga-0.1.dist-info/WHEEL
pandas_ga-0.1.dist-info/top_level.txt
pandas_ga-0.1.dist-info/RECORD
